poetry_release/__init__.py
poetry_release/_config.py
poetry_release/_default.py
poetry_release/_poetry_plugin.py
poetry_release/_util.py
poetry_release/plugin_api.py
nr.poetry_release-0.1.3.dist-info/entry_points.txt
nr.poetry_release-0.1.3.dist-info/WHEEL
nr.poetry_release-0.1.3.dist-info/METADATA
nr.poetry_release-0.1.3.dist-info/RECORD
