Metadata-Version: 2.1
Name: nr.poetry-release
Version: 0.1.3
Summary: A Poetry plugin to automate the release process of Python packages.
Author: Niklas Rosenstein
Author-email: rosensteinniklas@gmail.com
Requires-Python: >=3.10,<4.0
Classifier: Programming Language :: Python :: 3
Classifier: Programming Language :: Python :: 3.10
Requires-Dist: databind.json (>=1.4.0,<2.0.0)
Requires-Dist: nr.util (>=0.4.5,<0.5.0)
Requires-Dist: poetry (>=1.2.0a2,<2.0.0)
Requires-Dist: tomli (>=2.0.0,<3.0.0)
